Metadata-Version: 2.1
Name: methlab
Version: 0.9.2
Summary: Python tools for the epiclines ERC project
Home-page: https://github.com/ellisztamas/methlab
Author: Tom Ellis
Author-email: thomas.ellis@gmi.oeaw.ac.at
License: MIT license
Keywords: methlab
Classifier: Development Status :: 2 - Pre-Alpha
Classifier: Intended Audience :: Developers
Classifier: License :: OSI Approved :: MIT License
Classifier: Natural Language :: English
Classifier: Programming Language :: Python :: 3
Classifier: Programming Language :: Python :: 3.6
Classifier: Programming Language :: Python :: 3.7
Classifier: Programming Language :: Python :: 3.8
Requires-Python: >=3.6
License-File: LICENSE
License-File: AUTHORS.rst
Requires-Dist: pandas
Requires-Dist: numpy
Requires-Dist: plotly
Requires-Dist: scikit-allel
